PyChecko-1.3.0.dist-info/METADATA
PyChecko-1.3.0.dist-info/RECORD
PyChecko-1.3.0.dist-info/WHEEL
PyChecko-1.3.0.dist-info/top_level.txt
pychecko/__init__.py
pychecko/pychecko.py
tests/__init__.py
tests/fix_module.py
tests/test_pychecko.py
