Metadata-Version: 2.1
Name: PyChecko
Version: 1.3.0
Summary: MicroFramework to compose instances in execution time
Home-page: https://github.com/viniciusfeitosa/pychecko/
Author: Vinicius Pacheco
Author-email: vfpweb@gmail.com
License: MIT
Platform: any
